odoo/addons/partner_multi_relation/README.rst
odoo/addons/partner_multi_relation/__init__.py
odoo/addons/partner_multi_relation/__manifest__.py
odoo/addons/partner_multi_relation/demo/res_partner_category_demo.xml
odoo/addons/partner_multi_relation/demo/res_partner_demo.xml
odoo/addons/partner_multi_relation/demo/res_partner_relation_demo.xml
odoo/addons/partner_multi_relation/demo/res_partner_relation_type_demo.xml
odoo/addons/partner_multi_relation/i18n/am.po
odoo/addons/partner_multi_relation/i18n/ar.po
odoo/addons/partner_multi_relation/i18n/bg.po
odoo/addons/partner_multi_relation/i18n/bs.po
odoo/addons/partner_multi_relation/i18n/ca.po
odoo/addons/partner_multi_relation/i18n/cs.po
odoo/addons/partner_multi_relation/i18n/da.po
odoo/addons/partner_multi_relation/i18n/de.po
odoo/addons/partner_multi_relation/i18n/el_GR.po
odoo/addons/partner_multi_relation/i18n/en_GB.po
odoo/addons/partner_multi_relation/i18n/es.po
odoo/addons/partner_multi_relation/i18n/es_AR.po
odoo/addons/partner_multi_relation/i18n/es_CL.po
odoo/addons/partner_multi_relation/i18n/es_CO.po
odoo/addons/partner_multi_relation/i18n/es_CR.po
odoo/addons/partner_multi_relation/i18n/es_DO.po
odoo/addons/partner_multi_relation/i18n/es_EC.po
odoo/addons/partner_multi_relation/i18n/es_ES.po
odoo/addons/partner_multi_relation/i18n/es_MX.po
odoo/addons/partner_multi_relation/i18n/es_PE.po
odoo/addons/partner_multi_relation/i18n/es_PY.po
odoo/addons/partner_multi_relation/i18n/es_VE.po
odoo/addons/partner_multi_relation/i18n/et.po
odoo/addons/partner_multi_relation/i18n/eu.po
odoo/addons/partner_multi_relation/i18n/fa.po
odoo/addons/partner_multi_relation/i18n/fi.po
odoo/addons/partner_multi_relation/i18n/fr.po
odoo/addons/partner_multi_relation/i18n/fr_CA.po
odoo/addons/partner_multi_relation/i18n/fr_CH.po
odoo/addons/partner_multi_relation/i18n/fr_FR.po
odoo/addons/partner_multi_relation/i18n/gl.po
odoo/addons/partner_multi_relation/i18n/gl_ES.po
odoo/addons/partner_multi_relation/i18n/he.po
odoo12_addon_partner_multi_relation-12.0.2.0.0.dist-info/METADATA
odoo12_addon_partner_multi_relation-12.0.2.0.0.dist-info/WHEEL
odoo12_addon_partner_multi_relation-12.0.2.0.0.dist-info/top_level.txt
odoo12_addon_partner_multi_relation-12.0.2.0.0.dist-info/RECORD
